liman_core/__init__.py
liman_core/conf.py
liman_core/errors.py
liman_core/languages.py
liman_core/py.typed
liman_core/registry.py
liman_core/utils.py
liman_core/base/__init__.py
liman_core/base/component.py
liman_core/base/schemas.py
liman_core/edge/schemas.py
liman_core/edge/dsl/__init__.py
liman_core/edge/dsl/grammar.py
liman_core/edge/dsl/transformer.py
liman_core/node_actor/__init__.py
liman_core/node_actor/actor.py
liman_core/node_actor/conditional_evaluator.py
liman_core/node_actor/errors.py
liman_core/node_actor/schemas.py
liman_core/nodes/__init__.py
liman_core/nodes/supported_types.py
liman_core/nodes/utils.py
liman_core/nodes/base/__init__.py
liman_core/nodes/base/node.py
liman_core/nodes/base/schemas.py
liman_core/nodes/function_node/__init__.py
liman_core/nodes/function_node/node.py
liman_core/nodes/function_node/schemas.py
liman_core/nodes/llm_node/__init__.py
liman_core/nodes/llm_node/node.py
liman_core/nodes/llm_node/schemas.py
liman_core/nodes/node/__init__.py
liman_core/nodes/node/node.py
liman_core/nodes/node/schemas.py
liman_core/nodes/tool_node/__init__.py
liman_core/nodes/tool_node/errors.py
liman_core/nodes/tool_node/node.py
liman_core/nodes/tool_node/schemas.py
liman_core/nodes/tool_node/utils.py
liman_core/plugins/__init__.py
liman_core/plugins/auth/__init__.py
liman_core/plugins/auth/plugin.py
liman_core/plugins/auth/schemas.py
liman_core/plugins/auth/service_account.py
liman_core/plugins/core/__init__.py
liman_core/plugins/core/base.py
liman_core/plugins/core/errors.py
liman_core/plugins/core/register.py
liman_core-0.1.0a3.dist-info/METADATA
liman_core-0.1.0a3.dist-info/WHEEL
liman_core-0.1.0a3.dist-info/RECORD
