Metadata-Version: 2.4
Name: liman_core
Version: 0.1.0a3
Summary: Liman AgentOps Core Library
Author-email: Guro Bokum <jiojiajiu@gmail.com>
License-Expression: MIT
Classifier: License :: OSI Approved :: MIT License
Classifier: Operating System :: OS Independent
Classifier: Programming Language :: Python :: 3
Requires-Python: >=3.10
Requires-Dist: langchain-core>=0.3.67
Requires-Dist: lark>=1.2.2
Requires-Dist: pydantic>=2.11.7
Requires-Dist: rich>=14.0.0
Requires-Dist: ruamel-yaml>=0.18.14
